owl2diagram/__init__.py
owl2diagram/__main__.py
owl2diagram/_version.py
owl2diagram/query.py
owl2diagram/uml.py
owl2diagram-0.1.2.dist-info/LICENSE
owl2diagram-0.1.2.dist-info/METADATA
owl2diagram-0.1.2.dist-info/WHEEL
owl2diagram-0.1.2.dist-info/entry_points.txt
owl2diagram-0.1.2.dist-info/top_level.txt
owl2diagram-0.1.2.dist-info/RECORD
