Metadata-Version: 2.1
Name: owl2diagram
Version: 0.1.2
Summary: Generate a diagram of a given ontology
Author-email: Jhon Toledo <ja.toledo@upm.es>
License: Apache License
Project-URL: Source, https://github.com/jatoledo/owl2diagram
Project-URL: Tracker, https://github.com/jatoledo/owl2diagram/issues
Project-URL: CI, https://github.com/jatoledo/owl2diagram/actions
Project-URL: History, https://github.com/jatoledo/owl2diagram/releases
Classifier: Programming Language :: Python
Classifier: Programming Language :: Python :: 3
License-File: LICENSE
Provides-Extra: dev
Requires-Dist: pip-tools ; extra == 'dev'
Requires-Dist: pytest ; extra == 'dev'
